[
    {
      "title": "Message from User123",
      "content": "Hey, how are you doing today?",
      "received": "10 minutes ago"
    },
    {
      "title": "Message from User456",
      "content": "Hello, hope you are having a great day!",
      "received": "5 minutes ago"
    },
    {
      "title": "Message from User789",
      "content": "Are we still on for the meeting later?",
      "received": "20 minutes ago"
    },
    {
      "title": "Message from User321",
      "content": "Don't forget to send me the report.",
      "received": "30 minutes ago"
    },
    {
      "title": "Message from User654",
      "content": "Can we reschedule our call to tomorrow?",
      "received": "1 hour ago"
    },
    {
      "title": "Message from User987",
      "content": "Thanks for the update, much appreciated!",
      "received": "2 hours ago"
    },
    {
      "title": "Message from User111",
      "content": "Hey, just checking in to see how things are going.",
      "received": "3 hours ago"
    },
    {
      "title": "Message from User222",
      "content": "Please review the attached document when you have time.",
      "received": "4 hours ago"
    },
    {
      "title": "Message from User333",
      "content": "Looking forward to catching up next week!",
      "received": "1 day ago"
    },
    {
      "title": "Message from User444",
      "content": "Quick question: do you have the latest project files?",
      "received": "2 days ago"
    }
  ]
  